{
  "title": "Hutki-Kanki - Po rezerwacie Góra Chełm",
  "images": [
    {
      "src" : "/images/galeria/hutkiKanki/20_1.jpg",
      "thumb" : "/images/galeria/hutkiKanki/20_1_mid.jpg",
      "copy" : "Hutki-Kanki",
      "author" : "Fot. R. Chybiorz / 07.2009",
      "description" : "Na skaju wsi Hutki-Kanki, przy parkingu leśnym,  znajduje się tablica informacyjna z oznaczoną trasą rowerową (czarne kropki), przyrodniczą ścieżką dydaktyczną 'Rozlewisko rzeki Centuria' (zielone kropki) i rezerwatem przyrody 'Góra Chełm'."
    },
    {
      "src" : "/images/galeria/hutkiKanki/20_2.jpg",
      "thumb" : "/images/galeria/hutkiKanki/20_2_mid.jpg",
      "copy" : "ul. Chełmska",
      "author" : "Fot. R. Chybiorz / 07.2009",
      "description" : "Na Górę Chełm dochodzimy od parkinku leśnego lub przystanku PKS wzdłuż ul. Chełmskiej, zielonym Szlakiem Tysiąclecia."
    },
    {
      "src" : "/images/galeria/hutkiKanki/20_3.jpg",
      "thumb" : "/images/galeria/hutkiKanki/20_3_mid.jpg",
      "copy" : "Rezerwat Góra Chełm",
      "author" : "Fot. R. Chybiorz / 07.2009",
      "description" : "Na końcu ul. Chełmskiej - zachodnia granica rezerwatu - jest czytelna tablica informacyjna."
    },
    {
      "src" : "/images/galeria/hutkiKanki/20_4.jpg",
      "thumb" : "/images/galeria/hutkiKanki/20_4_mid.jpg",
      "copy" : "Rezerwat Góra Chełm",
      "author" : "Fot. R. Chybiorz / 07.2009",
      "description" : "Czytelna tablica informacyjna znajduje się również we wschodniej części rezerwatu, na zielonym Szlaku Tysiąclecia."
    },
    {
      "src" : "/images/galeria/hutkiKanki/20_5.jpg",
      "thumb" : "/images/galeria/hutkiKanki/20_5_mid.jpg",
      "copy" : "Ścieżka przyrodnicza",
      "author" : "Fot. R. Chybiorz / 07.2009",
      "description" : "Na szlaku zielonym, zarówno od strony zachodniej i wschodniej wzniesienia, są także tablice informacyjne ścieżki przyrodniczej."
    },
    {
      "src" : "/images/galeria/hutkiKanki/20_6.jpg",
      "thumb" : "/images/galeria/hutkiKanki/20_6_mid.jpg",
      "copy" : "Ścieżka przyrodnicza",
      "author" : "Fot. R. Chybiorz / 07.2009",
      "description" : "Szkic trasy ścieżki jest za mały i umieszczony za wysoko, a 6 (7?) przystanków nie miało w lipcu 2009 r. swoich tablic informacyjnych."
    },
    {
      "src" : "/images/galeria/hutkiKanki/20_7.jpg",
      "thumb" : "/images/galeria/hutkiKanki/20_7_mid.jpg",
      "copy" : "Góra Chełm",
      "author" : "Fot. R. Chybiorz / 07.2009",
      "description" : "Widok na Górę Chełm (440 m n.p.m.) od strony parkingu leśnego."
    },
    {
      "src" : "/images/galeria/hutkiKanki/20_8.jpg",
      "thumb" : "/images/galeria/hutkiKanki/20_8_mid.jpg",
      "copy" : "Ścieżka przyrodnicza",
      "author" : "Fot. R. Chybiorz / 07.2009",
      "description" : "Trasa ścieżki przyrodniczej jest dobrze oznakowana na drzewach."
    },
    {
      "src" : "/images/galeria/hutkiKanki/20_9.jpg",
      "thumb" : "/images/galeria/hutkiKanki/20_9_mid.jpg",
      "copy" : "Ostańce wapienne",
      "author" : "Fot. R. Chybiorz / 07.2009",
      "description" : "Na wzgórzu znajduje się 7 dużych i 10 małych ostanców wapiennych pochodzących z okresu jurajskiego."
    },
    {
      "src" : "/images/galeria/hutkiKanki/20_10.jpg",
      "thumb" : "/images/galeria/hutkiKanki/20_10_mid.jpg",
      "copy" : "Wapienne wzgórze",
      "author" : "Fot. R. Chybiorz / 07.2009",
      "description" : "Wapienne wzgórze porasta las bukowy o charakterze naturalnym."
    },
    {
      "src" : "/images/galeria/hutkiKanki/20_12.jpg",
      "thumb" : "/images/galeria/hutkiKanki/20_12_mid.jpg",
      "copy" : "Ostańce wapienne",
      "author" : "Fot. R. Chybiorz / 07.2009",
      "description" : "W wapiennych skałach można odnaleź muszle ramienionogów, przekroje gąbek oraz ślady po glonach. Skamieniałości są źródłem informacji o morzach, w ktorych powstały wapienie."
    },
    {
      "src" : "/images/galeria/hutkiKanki/20_13.jpg",
      "thumb" : "/images/galeria/hutkiKanki/20_13_mid.jpg",
      "copy" : "Ostańce wapienne",
      "author" : "Fot. R. Chybiorz / 07.2009",
      "description" : "Wapienie dostarczają także wiadomości na temat klimatu jaki panował w okresie jurajskim."
    }
  ]
}
